fpt_pytest_tools/__init__.py
fpt_pytest_tools-0.2.0.dist-info/METADATA
fpt_pytest_tools-0.2.0.dist-info/WHEEL
fpt_pytest_tools-0.2.0.dist-info/top_level.txt
fpt_pytest_tools-0.2.0.dist-info/RECORD
