Metadata-Version: 2.2
Name: fpt_pytest_tools
Version: 0.2.0
Summary: Pytest tools to use with our systems (FPT).
Author-email: Francisco Mabres <francisco.mabres@fisherpaykel.com>
Classifier: Programming Language :: Python
Classifier: Programming Language :: Python :: 3
Classifier: Programming Language :: Python :: 3 :: Only
Classifier: Programming Language :: Python :: 3.8
Classifier: Programming Language :: Python :: 3.9
Classifier: Programming Language :: Python :: 3.10
Classifier: Programming Language :: Python :: 3.11
Classifier: Programming Language :: Python :: 3.12
Classifier: Programming Language :: Python :: 3.13
Classifier: Intended Audience :: Developers
Classifier: Operating System :: Unix
Classifier: Operating System :: POSIX :: Linux
Classifier: Environment :: Console
Classifier: Environment :: MacOS X
Classifier: Framework :: Pytest
Classifier: Topic :: Software Development :: Libraries :: Python Modules
Requires-Python: >=3.8
